LICENSE.txt
MANIFEST.in
README.rst
setup.py
aiidalab_vapory.egg-info/PKG-INFO
aiidalab_vapory.egg-info/SOURCES.txt
aiidalab_vapory.egg-info/dependency_links.txt
aiidalab_vapory.egg-info/top_level.txt
examples/_run_all_examples.py
examples/chessboard.py
examples/cube.py
examples/focal.py
examples/lens.py
examples/octagons.py
examples/pawn.py
examples/radiosity.py
examples/sphere.py
examples/spiral.py
vapory/__init__.py
vapory/config.py
vapory/helpers.py
vapory/io.py
vapory/vapory.py
vapory/version.py